[{"id":"158023","name":"Lionel Messi","rating":"94","photo":"./data/images/photos/0/158023.png","club":{"name":"FC Barcelone","logo":"./data/images/clubs/FCBarcelone.png"},"positions":["ATT","BU","AD"],"photoFolderIndex":0,"shortName":"Messi"},{"id":"180206","name":"Miralem Pjanić","rating":"86","photo":"./data/images/photos/1/180206.png","club":{"name":"Juventus","logo":"./data/images/clubs/Juventus.png"},"positions":["MC","MDC"],"photoFolderIndex":1,"shortName":"Pjanić"},{"id":"204963","name":"Carvajal","rating":"84","photo":"./data/images/photos/2/204963.png","club":{"name":"Real Madrid","logo":"./data/images/clubs/RealMadrid.png"},"positions":["DD"],"photoFolderIndex":2,"shortName":"Carvajal"},{"id":"1179","name":"Gianluigi Buffon","rating":"89","photo":"./data/images/photos/4/1179.png","club":{"name":"Juventus","logo":"./data/images/clubs/Juventus.png"},"positions":["G"],"photoFolderIndex":4,"shortName":"Buffon"},{"id":"226537","name":"Vincent Janssen","rating":"77","photo":"./data/images/photos/0/226537.png","club":{"name":"Fenerbahçe","logo":"./data/images/clubs/Fenerbahce.png"},"positions":["BU"],"photoFolderIndex":0,"shortName":"Janssen"},{"id":"198009","name":"Mattia Perin","rating":"84","photo":"./data/images/photos/3/198009.png","club":{"name":"Genoa","logo":"./data/images/clubs/Genoa.png"},"positions":["G"],"photoFolderIndex":3,"shortName":"Perin"},{"id":"155862","name":"Sergio Ramos","rating":"90","photo":"./data/images/photos/1/155862.png","club":{"name":"Real Madrid","logo":"./data/images/clubs/RealMadrid.png"},"positions":["DC"],"photoFolderIndex":1,"shortName":"Ramos"},{"id":"20801","name":"Cristiano Ronaldo","rating":"94","photo":"./data/images/photos/1/20801.png","club":{"name":"Real Madrid","logo":"./data/images/clubs/RealMadrid.png"},"positions":["AG","BU"],"photoFolderIndex":1,"shortName":"Ronaldo"},{"id":"183280","name":"Adil Rami","rating":"81","photo":"./data/images/photos/4/183280.png","club":{"name":"OM","logo":"./data/images/clubs/OM.png"},"positions":["DC"],"photoFolderIndex":4,"shortName":"Rami"},{"id":"208418","name":"Yannick Carrasco","rating":"85","photo":"./data/images/photos/1/208418.png","club":{"name":"Agents libres","logo":"./data/images/clubs/Agentslibres.png"},"positions":["MG","MD"],"photoFolderIndex":1,"shortName":"Carrasco"},{"id":"20801","name":"Cristiano Ronaldo","rating":"94","photo":"./data/images/photos/1/20801.png","club":{"name":"Real Madrid","logo":"./data/images/clubs/RealMadrid.png"},"positions":["AG","BU"],"photoFolderIndex":1,"shortName":"Ronaldo"}]